k2plr/__init__.py
k2plr/api.py
k2plr/config.py
k2plr/huber.py
k2plr/kplr.py
k2plr/ld.py
k2plr/mast.py
k2plr-0.2.9.dist-info/METADATA
k2plr-0.2.9.dist-info/RECORD
k2plr-0.2.9.dist-info/WHEEL
k2plr-0.2.9.dist-info/top_level.txt
